{
  "id": "07-03-workflow-durable-run-events",
  "name": "07-03-workflow-durable-run-events",
  "title": "Implement Workflow Durable Run Event History",
  "description": "Add the first durable workflow core slice: append-only workflow run event records, idempotency keys, and read-only trace/diagnostic integration without adding workflow-owned executors, tools, timers, or parallel DAG scheduling.",
  "status": "completed",
  "dev_type": null,
  "scope": null,
  "package": null,
  "priority": "P0",
  "creator": "vimalinx",
  "assignee": "vimalinx",
  "createdAt": "2026-07-03",
  "completedAt": "2026-07-07",
  "branch": null,
  "base_branch": "main",
  "worktree_path": null,
  "commit": null,
  "pr_url": null,
  "subtasks": [],
  "children": [],
  "parent": null,
  "relatedFiles": [],
  "notes": "",
  "meta": {}
}